enrich2/__init__.py
enrich2/aligner.py
enrich2/barcode.py
enrich2/barcodeid.py
enrich2/barcodemap.py
enrich2/barcodevariant.py
enrich2/basic.py
enrich2/condition.py
enrich2/config_check.py
enrich2/constants.py
enrich2/dataframe.py
enrich2/experiment.py
enrich2/fastqheader.py
enrich2/idonly.py
enrich2/main.py
enrich2/overlap.py
enrich2/plots.py
enrich2/random_effects.py
enrich2/selection.py
enrich2/seqlib.py
enrich2/sfmap.py
enrich2/storemanager.py
enrich2/variant.py
enrich2/wildtype.py
enrich2/ztest.py
enrich2/gui/__init__.py
enrich2/gui/configurator.py
enrich2/gui/create_root_dialog.py
enrich2/gui/create_seqlib_dialog.py
enrich2/gui/delete_dialog.py
enrich2/gui/dialog_elements.py
enrich2/gui/edit_dialog.py
enrich2/gui/runner_window.py
enrich2/gui/seqlib_apply_dialog.py
enrich2-2.0.2.dist-info/METADATA
enrich2-2.0.2.dist-info/WHEEL
enrich2-2.0.2.dist-info/entry_points.txt
enrich2-2.0.2.dist-info/licenses/LICENSE
enrich2-2.0.2.dist-info/RECORD
