Metadata-Version: 2.4
Name: Enrich2
Version: 2.0.2
Summary: Analysis program for calculating variant scores from deep mutational scanning data.
Project-URL: Homepage, https://github.com/FowlerLab/Enrich2/
Author-email: Alan F Rubin <alan.rubin@wehi.edu.au>
License-Expression: BSD-3-Clause
License-File: LICENSE
Requires-Dist: fqfa
Requires-Dist: matplotlib
Requires-Dist: numpy
Requires-Dist: pandas
Requires-Dist: scipy
Requires-Dist: statsmodels
Requires-Dist: tables
